
main <sum.lua:0,0> (11 instructions at 0000000000a58a50)
0+ params, 6 slots, 1 upvalue, 5 locals, 4 constants, 0 functions
	1	[2]	LOADK    	0 -1	; 0
	2	[3]	LOADK    	1 -2	; 1
	3	[3]	LOADK    	2 -3	; 100
	4	[3]	LOADK    	3 -2	; 1
	5	[3]	FORPREP  	1 4	; to 10
	6	[4]	MOD      	5 4 -4	; - 2
	7	[4]	EQ       	0 5 -1	; - 0
	8	[4]	JMP      	0 1	; to 10
	9	[5]	ADD      	0 0 4
	10	[3]	FORLOOP  	1 -5	; to 6
	11	[7]	RETURN   	0 1
constants (4) for 0000000000a58a50:
	1	0
	2	1
	3	100
	4	2
locals (5) for 0000000000a58a50:
	0	sum	2	12
	1	(for index)	5	11
	2	(for limit)	5	11
	3	(for step)	5	11
	4	i	6	10
upvalues (1) for 0000000000a58a50:
	0	_ENV	1	0
