
main <page_202_test.lua:0,0> (29 instructions at 0000000000ba8ac0)
0+ params, 2 slots, 1 upvalue, 0 locals, 4 constants, 1 function
	1	[9]	CLOSURE  	0 0	; 0000000000ba8c30
	2	[3]	SETTABUP 	0 -1 0	; _ENV "newCounter"
	3	[11]	GETTABUP 	0 0 -1	; _ENV "newCounter"
	4	[11]	CALL     	0 1 2
	5	[11]	SETTABUP 	0 -2 0	; _ENV "c1"
	6	[12]	GETTABUP 	0 0 -3	; _ENV "print"
	7	[12]	GETTABUP 	1 0 -2	; _ENV "c1"
	8	[12]	CALL     	1 1 0
	9	[12]	CALL     	0 0 1
	10	[13]	GETTABUP 	0 0 -3	; _ENV "print"
	11	[13]	GETTABUP 	1 0 -2	; _ENV "c1"
	12	[13]	CALL     	1 1 0
	13	[13]	CALL     	0 0 1
	14	[15]	GETTABUP 	0 0 -1	; _ENV "newCounter"
	15	[15]	CALL     	0 1 2
	16	[15]	SETTABUP 	0 -4 0	; _ENV "c2"
	17	[16]	GETTABUP 	0 0 -3	; _ENV "print"
	18	[16]	GETTABUP 	1 0 -4	; _ENV "c2"
	19	[16]	CALL     	1 1 0
	20	[16]	CALL     	0 0 1
	21	[17]	GETTABUP 	0 0 -3	; _ENV "print"
	22	[17]	GETTABUP 	1 0 -2	; _ENV "c1"
	23	[17]	CALL     	1 1 0
	24	[17]	CALL     	0 0 1
	25	[18]	GETTABUP 	0 0 -3	; _ENV "print"
	26	[18]	GETTABUP 	1 0 -4	; _ENV "c2"
	27	[18]	CALL     	1 1 0
	28	[18]	CALL     	0 0 1
	29	[18]	RETURN   	0 1
constants (4) for 0000000000ba8ac0:
	1	"newCounter"
	2	"c1"
	3	"print"
	4	"c2"
locals (0) for 0000000000ba8ac0:
upvalues (1) for 0000000000ba8ac0:
	0	_ENV	1	0

function <page_202_test.lua:3,9> (4 instructions at 0000000000ba8c30)
0 params, 2 slots, 0 upvalues, 1 local, 1 constant, 1 function
	1	[4]	LOADK    	0 -1	; 0
	2	[8]	CLOSURE  	1 0	; 0000000000ba8e50
	3	[8]	RETURN   	1 2
	4	[9]	RETURN   	0 1
constants (1) for 0000000000ba8c30:
	1	0
locals (1) for 0000000000ba8c30:
	0	count	2	5
upvalues (0) for 0000000000ba8c30:

function <page_202_test.lua:5,8> (6 instructions at 0000000000ba8e50)
0 params, 2 slots, 1 upvalue, 0 locals, 1 constant, 0 functions
	1	[6]	GETUPVAL 	0 0	; count
	2	[6]	ADD      	0 0 -1	; - 1
	3	[6]	SETUPVAL 	0 0	; count
	4	[7]	GETUPVAL 	0 0	; count
	5	[7]	RETURN   	0 2
	6	[8]	RETURN   	0 1
constants (1) for 0000000000ba8e50:
	1	1
locals (0) for 0000000000ba8e50:
upvalues (1) for 0000000000ba8e50:
	0	count	1	0
