
main <page_195_GETUPVAL.lua:0,0> (4 instructions at 0000000000c18ac0)
0+ params, 4 slots, 1 upvalue, 3 locals, 1 constant, 1 function
	1	[2]	LOADNIL  	0 2
	2	[5]	CLOSURE  	3 0	; 0000000000c18dd0
	3	[3]	SETTABUP 	0 -1 3	; _ENV "f"
	4	[5]	RETURN   	0 1
constants (1) for 0000000000c18ac0:
	1	"f"
locals (3) for 0000000000c18ac0:
	0	u	2	5
	1	v	2	5
	2	w	2	5
upvalues (1) for 0000000000c18ac0:
	0	_ENV	1	0

function <page_195_GETUPVAL.lua:3,5> (6 instructions at 0000000000c18dd0)
0 params, 5 slots, 3 upvalues, 5 locals, 2 constants, 0 functions
	1	[4]	LOADK    	0 -1	; 1
	2	[4]	LOADK    	1 -2	; 2
	3	[4]	GETUPVAL 	2 0	; u
	4	[4]	GETUPVAL 	3 1	; v
	5	[4]	GETUPVAL 	4 2	; w
	6	[5]	RETURN   	0 1
constants (2) for 0000000000c18dd0:
	1	1
	2	2
locals (5) for 0000000000c18dd0:
	0	a	6	7
	1	b	6	7
	2	c	6	7
	3	d	6	7
	4	e	6	7
upvalues (3) for 0000000000c18dd0:
	0	u	1	0
	1	v	1	1
	2	w	1	2
