
main <page_198_GETTABUP.lua:0,0> (4 instructions at 0000000000bf8ac0)
0+ params, 2 slots, 1 upvalue, 1 local, 1 constant, 1 function
	1	[2]	LOADNIL  	0 0
	2	[7]	CLOSURE  	1 0	; 0000000000bf8ce0
	3	[3]	SETTABUP 	0 -1 1	; _ENV "f"
	4	[7]	RETURN   	0 1
constants (1) for 0000000000bf8ac0:
	1	"f"
locals (1) for 0000000000bf8ac0:
	0	u	2	5
upvalues (1) for 0000000000bf8ac0:
	0	_ENV	1	0

function <page_198_GETTABUP.lua:3,7> (4 instructions at 0000000000bf8ce0)
0 params, 5 slots, 1 upvalue, 5 locals, 1 constant, 0 functions
	1	[4]	LOADNIL  	0 4
	2	[5]	GETTABUP 	3 0 2	; u
	3	[6]	GETTABUP 	3 0 -1	; u 100
	4	[7]	RETURN   	0 1
constants (1) for 0000000000bf8ce0:
	1	100
locals (5) for 0000000000bf8ce0:
	0	a	2	5
	1	b	2	5
	2	k	2	5
	3	d	2	5
	4	e	2	5
upvalues (1) for 0000000000bf8ce0:
	0	u	1	0
