
main <page_200_JMP.lua:0,0> (5 instructions at 0000000000708ac0)
0+ params, 7 slots, 1 upvalue, 6 locals, 1 constant, 1 function
	1	[2]	LOADNIL  	0 5
	2	[7]	CLOSURE  	6 0	; 0000000000708cc0
	3	[5]	SETTABUP 	0 -1 6	; _ENV "foo"
	4	[7]	JMP      	4 0	; to 5
	5	[8]	RETURN   	0 1
constants (1) for 0000000000708ac0:
	1	"foo"
locals (6) for 0000000000708ac0:
	0	x	2	6
	1	y	2	6
	2	z	2	6
	3	a	2	5
	4	b	2	5
	5	c	2	5
upvalues (1) for 0000000000708ac0:
	0	_ENV	1	0

function <page_200_JMP.lua:5,7> (3 instructions at 0000000000708cc0)
0 params, 2 slots, 1 upvalue, 0 locals, 1 constant, 0 functions
	1	[6]	LOADK    	0 -1	; 1
	2	[6]	SETUPVAL 	0 0	; b
	3	[7]	RETURN   	0 1
constants (1) for 0000000000708cc0:
	1	1
locals (0) for 0000000000708cc0:
upvalues (1) for 0000000000708cc0:
	0	b	1	4
