
main <upvalue_add_case1.lua:0,0> (7 instructions at 0000000000ce8ac0)
0+ params, 3 slots, 1 upvalue, 1 local, 3 constants, 1 function
	1	[1]	LOADK    	0 -1	; 99
	2	[4]	CLOSURE  	1 0	; 0000000000ce8c30
	3	[2]	SETTABUP 	0 -2 1	; _ENV "f"
	4	[5]	GETTABUP 	1 0 -3	; _ENV "print"
	5	[5]	MOVE     	2 0
	6	[5]	CALL     	1 2 1
	7	[5]	RETURN   	0 1
constants (3) for 0000000000ce8ac0:
	1	99
	2	"f"
	3	"print"
locals (1) for 0000000000ce8ac0:
	0	x	2	8
upvalues (1) for 0000000000ce8ac0:
	0	_ENV	1	0

function <upvalue_add_case1.lua:2,4> (4 instructions at 0000000000ce8c30)
0 params, 2 slots, 1 upvalue, 0 locals, 1 constant, 0 functions
	1	[3]	GETUPVAL 	0 0	; x
	2	[3]	ADD      	0 0 -1	; - 1
	3	[3]	SETUPVAL 	0 0	; x
	4	[4]	RETURN   	0 1
constants (1) for 0000000000ce8c30:
	1	1
locals (0) for 0000000000ce8c30:
upvalues (1) for 0000000000ce8c30:
	0	x	1	0
